sbm/ISBM.py
sbm/SBM.py
sbm/TFBM.py
sbm/__init__.py
sbm/constants.py
sbm/main.py
space_breakdown_method-0.0.2.dist-info/LICENSE.txt
space_breakdown_method-0.0.2.dist-info/METADATA
space_breakdown_method-0.0.2.dist-info/WHEEL
space_breakdown_method-0.0.2.dist-info/top_level.txt
space_breakdown_method-0.0.2.dist-info/RECORD
