Metadata-Version: 2.1
Name: space-breakdown-method
Version: 0.0.2
Summary: Space Breakdown Method (SBM) is a clustering algorithm developed for Spike Sorting handling overlapping and imbalanced data. Improved Space Breakdown Method (ISBM) is the updated and improved version of SBM. A new algorithm for the detection of brain oscillations packets has been developed based on SBM, called Time-Frequency Breakdown Method (TFBM)
Home-page: https://https://github.com/ArdeleanRichard/Space-Breakdown-Method
Author: Eugen-Richard Ardelean
Author-email: ardeleaneugenrichard@gmail.com
License: MIT
Classifier: License :: OSI Approved :: MIT License
Classifier: Programming Language :: Python :: 3.7
Classifier: Operating System :: OS Independent
Requires-Python: >=3.7
License-File: LICENSE.txt
Requires-Dist: numpy
Requires-Dist: scikit-learn
Requires-Dist: matplotlib
Requires-Dist: scipy
Requires-Dist: networkx
Requires-Dist: plotly
Requires-Dist: pandas
Provides-Extra: dev
Requires-Dist: twine >=4.0.2 ; extra == 'dev'
